p2json/__init__.py
p2json-0.1.2.dist-info/METADATA
p2json-0.1.2.dist-info/WHEEL
p2json-0.1.2.dist-info/RECORD
