Metadata-Version: 2.3
Name: p2json
Version: 0.1.2
Summary: jsonp to json converter
Author: zoushucai
Author-email: zoushucai@users.noreply.github.com
Requires-Python: >=3.3
Classifier: Programming Language :: Python :: 3
Classifier: Programming Language :: Python :: 3.4
Classifier: Programming Language :: Python :: 3.5
Classifier: Programming Language :: Python :: 3.6
Classifier: Programming Language :: Python :: 3.7
Classifier: Programming Language :: Python :: 3.8
Classifier: Programming Language :: Python :: 3.9
Classifier: Programming Language :: Python :: 3.10
Classifier: Programming Language :: Python :: 3.11
Classifier: Programming Language :: Python :: 3.12
Classifier: Programming Language :: Python :: 3.13
Project-URL: Homepage, https://github.com/zoushucai/p2json
Project-URL: Repository, https://github.com/zoushucai/p2json
